restools/__init__.py
restools/configure/__init__.py
restools/configure/configure.py
restools/logging/__init__.py
restools/logging/logger_base.py
restools/plotting/__init__.py
restools/plotting/plot_2D.py
restools/serving/__init__.py
restools/serving/shserver.py
restools-0.0.1.2.dist-info/licenses/LICENSE
restools-0.0.1.2.dist-info/METADATA
restools-0.0.1.2.dist-info/WHEEL
restools-0.0.1.2.dist-info/top_level.txt
restools-0.0.1.2.dist-info/RECORD
